<?xml version="1.0" encoding="UTF-8"?>
<ObservationDefinition xmlns="http://hl7.org/fhir">
   <id value="observation-definition-loinc-804-5"/>
   <text>
      <status value="generated"/>
      <div xmlns="http://www.w3.org/1999/xhtml">Observation for Leukocytes [#/volume] in Blood by Manual count</div>
   </text>
   <code>
      <coding>
         <system value="http://loinc.org"/>
         <code value="804-5"/>
         <display value="Leukocytes [#/volume] in Blood by Manual count"/>
      </coding>
   </code>
</ObservationDefinition>
