{"resourceType":"ActivityDefinition","id":"activity-definition-loinc-53857-9","text":{"status":"generated","div":"<div xmlns=\"http://www.w3.org/1999/xhtml\">Activity Definition for Hemoglobin F [Mass/volume] in Blood</div>"},"url":"https://rarecare.world/53857-9","status":"draft","description":"Hemoglobin F [Mass/volume] in Blood Measurement","kind":"ServiceRequest","code":{"text":"Hemoglobin F [Mass/volume] in Blood"},"observationResultRequirement":[{"reference":"observation-definition-53857-9"}]}